{
  "state": "stopped",
  "intervalMinutes": 30,
  "discoveryBatchSize": 250,
  "discoveryEnabled": true,
  "updatedAt": "2026-07-07T04:36:29.296Z",
  "cycleNumber": 1,
  "cycleStartedAt": "2026-07-07T04:19:00.540Z",
  "lastError": null,
  "currentStep": null,
  "lastSuccessfulCycleAt": "2026-07-07T04:36:29.294Z",
  "lastCycleStartedAt": "2026-07-07T04:19:00.540Z",
  "nextRunAt": null,
  "companyCatalogSize": 1649,
  "configuredCompanies": 554,
  "unconfiguredCompanies": 1095,
  "sourceCounts": {
    "generic": 127,
    "unconfigured": 1095,
    "smartrecruiters": 42,
    "workday": 35,
    "greenhouse": 246,
    "ashby": 34,
    "lever": 68,
    "microsoft": 1,
    "icims": 1
  },
  "jobCount": 3736,
  "jobSourceCounts": {
    "Apple Jobs official site": 6,
    "Google Careers official site": 19,
    "Greenhouse career portal": 2718,
    "Lever career portal": 217,
    "SmartRecruiters career portal": 215,
    "Amazon Jobs official site": 206,
    "Microsoft career portal": 6,
    "Ashby career portal": 333,
    "Flipkart Careers official site": 8,
    "Company career site (structured data)": 8
  },
  "jobsGeneratedAt": "2026-07-07T04:36:29.209Z",
  "atsDiscoveryBatchSize": 250,
  "webDiscoveryBatchSize": 120
}
